poxls/__init__.py
poxls/po_to_xls.py
poxls/xls_to_po.py
poxls-1.6.2.dist-info/METADATA
poxls-1.6.2.dist-info/WHEEL
poxls-1.6.2.dist-info/entry_points.txt
poxls-1.6.2.dist-info/top_level.txt
poxls-1.6.2.dist-info/zip-safe
poxls-1.6.2.dist-info/RECORD
