Metadata-Version: 1.1
Name: poxls
Version: 1.6.2
Summary: Convert between Excel and PO files
Home-page: https://github.com/wichert/po-xls
Author: Wichert Akkerman
Author-email: wichert@wiggy.net
License: BSD
Keywords: translation po gettext Babel lingua
Platform: UNKNOWN
Classifier: Environment :: Console
Classifier: Intended Audience :: Developers
Classifier: License :: DFSG approved
Classifier: License :: OSI Approved :: BSD License
Classifier: Operating System :: OS Independent
Classifier: Programming Language :: Python :: 2
Classifier: Programming Language :: Python :: 2.6
Classifier: Programming Language :: Python :: 2.7
Classifier: Programming Language :: Python :: 3
Classifier: Intended Audience :: Developers
Classifier: Intended Audience :: End Users/Desktop
